task3/ram.sv
module ram #(
    parameter ADDRESS_WIDTH = 8,
    DATA_WIDTH = 8
)(
    input logic clk,
    input logic wr,
    input logic rd,
    input logic [ADDRESS_WIDTH-1:0] offset,
    input logic [ADDRESS_WIDTH-1:0] rd_addr,
    input logic [DATA_WIDTH-1:0] din,
    output logic [DATA_WIDTH-1:0] dout_write,
    output logic [DATA_WIDTH-1:0] dout_read
);

logic [DATA_WIDTH-1:0] ram_array [2**ADDRESS_WIDTH-1:0]; //2^something 
logic [ADDRESS_WIDTH-1:0] wr_addr;
//because you can't get input from input(rd_addr and offset), you have to define wr addr as an intermediate logic

always_ff @(posedge clk) begin
    if (wr == 1'b1)
        wr_addr <= rd_addr + offset;
        ram_array [wr_addr] <= din;
        dout_write <= ram_array [wr_addr]; //when writing to the ram, the task also asks you to print the value stored in the ram, hence you need this extra line.
    if (rd == 1'b1)
    // output is synchronous
        dout_read <= ram_array [rd_addr];
end
endmodule

task3/counter.sv
module counter #(
    parameter WIDTH = 8
)(
    //interface signals
    input logic         clk, //clock
    input logic         rst, //reset
    input logic         en,  //counter enable
   input logic  [WIDTH-1:0]      incr,
    output logic [WIDTH-1:0]       count //count output
);

always_ff @ (posedge clk)
if (rst ) count <={WIDTH{1'b0}};
else if (en) count <= count + incr;


endmodule

task3/sigdelay.sv
module sigdelay #(
    parameter WIDTH = 8,
    ADDRESS_WIDTH = 8,
    DATA_WIDTH = 8
)(
    input logic clk,
    input logic en,
    input logic rst,
    input logic [WIDTH-1:0] incr,
    input logic wr,
    input logic rd,
    input logic [ADDRESS_WIDTH-1:0] offset,
    input logic [DATA_WIDTH-1:0] din,
    output logic [DATA_WIDTH-1:0] mic_signal,
    output logic [DATA_WIDTH-1:0] delayed_signal
);
 
    logic  [ADDRESS_WIDTH-1:0]      addr;

counter mycounter(
  .clk (clk),
  .rst (rst),
  .en (en),
  .count (addr),
  .incr (incr)
);



ram myram(
    .clk (clk),
    .rd_addr (addr),
    .offset (offset),
    .din (din),
    .rd (rd),
    .wr (wr),
    .dout_read (mic_signal),
    .dout_write(delayed_signal)
);

endmodule

task3/sigdelay.vcd
$version Generated by VerilatedVcd $end
$date Sun Oct 30 18:30:47 2022 $end
$timescale 1ps $end

 $scope module TOP $end
  $var wire  1 # clk $end
  $var wire  8 , delayed_signal [7:0] $end
  $var wire  8 * din [7:0] $end
  $var wire  1 $ en $end
  $var wire  8 & incr [7:0] $end
  $var wire  8 + mic_signal [7:0] $end
  $var wire  8 ) offset [7:0] $end
  $var wire  1 ( rd $end
  $var wire  1 % rst $end
  $var wire  1 ' wr $end
  $scope module sigdelay $end
   $var wire 32 / ADDRESS_WIDTH [31:0] $end
   $var wire 32 / DATA_WIDTH [31:0] $end
   $var wire 32 / WIDTH [31:0] $end
   $var wire  8 - addr [7:0] $end
   $var wire  1 # clk $end
   $var wire  8 , delayed_signal [7:0] $end
   $var wire  8 * din [7:0] $end
   $var wire  1 $ en $end
   $var wire  8 & incr [7:0] $end
   $var wire  8 + mic_signal [7:0] $end
   $var wire  8 ) offset [7:0] $end
   $var wire  1 ( rd $end
   $var wire  1 % rst $end
   $var wire  1 ' wr $end
   $scope module mycounter $end
    $var wire 32 / WIDTH [31:0] $end
    $var wire  1 # clk $end
    $var wire  8 - count [7:0] $end
    $var wire  1 $ en $end
    $var wire  8 & incr [7:0] $end
    $var wire  1 % rst $end
   $upscope $end
   $scope module myram $end
    $var wire 32 / ADDRESS_WIDTH [31:0] $end
    $var wire 32 / DATA_WIDTH [31:0] $end
    $var wire  1 # clk $end
    $var wire  8 * din [7:0] $end
    $var wire  8 + dout_read [7:0] $end
    $var wire  8 , dout_write [7:0] $end
    $var wire  8 ) offset [7:0] $end
    $var wire  1 ( rd $end
    $var wire  8 - rd_addr [7:0] $end
    $var wire  1 ' wr $end
    $var wire  8 . wr_addr [7:0] $end
   $upscope $end
  $upscope $end
 $upscope $end
$enddefinitions $end


#0
1#
0$
0%
b00000000 &
1'
1(
b01000000 )
b00000000 *
b00000000 +
b00000000 ,
b00000000 -
b00000000 .
b00000000000000000000000000001000 /
#1
0#
#2
1#
b01100110 +
b01000000 .
#3
0#
#4
1#
b01011011 +
#5
0#
#6
1#
b01001010 +
#7
0#
#8
1#
b01001100 +
#9
0#
#10
1#
b01011100 +
#11
0#
#12
1#
b01101101 +
#13
0#
#14
1#
b01100100 +
#15
0#
#16
1#
b01100111 +
#17
0#
#18
1#
b01111000 +
#19
0#
#20
1#
b10000010 +
#21
0#
#22
1#
b01011001 +
#23
0#
#24
1#
b01100100 +
#25
0#
#26
1#
b01101100 +
#27
0#
#28
1#
b01100000 +
#29
0#
#30
1#
#31
0#
#32
1#
b01101111 +
#33
0#
#34
1#
b01110001 +
#35
0#
#36
1#
b01110100 +
#37
0#
#38
1#
b01100110 +
#39
0#
#40
1#
b01101000 +
#41
0#
#42
1#
b01011000 +
#43
0#
#44
1#
b01100011 +
#45
0#
#46
1#
b01011011 +
#47
0#
#48
1#
b01111001 +
#49
0#
#50
1#
b01101101 +
#51
0#
#52
1#
b01100111 +
#53
0#
#54
1#
b01101101 +
#55
0#
#56
1#
b01101000 +
#57
0#
#58
1#
b01111111 +
#59
0#
#60
1#
b10000010 +
#61
0#
#62
1#
b10001010 +
#63
0#
#64
1#
b01111111 +
#65
0#
#66
1#
b10000010 +
#67
0#
#68
1#
b10000111 +
#69
0#
#70
1#
b10000110 +
#71
0#
#72
1#
b01111110 +
#73
0#
#74
1#
b01110001 +
#75
0#
#76
1#
b01101111 +
#77
0#
#78
1#
b01100101 +
#79
0#
#80
1#
b01011100 +
#81
0#
#82
1#
b01001110 +
#83
0#
#84
1#
b01001011 +
#85
0#
#86
1#
b01001000 +
#87
0#
#88
1#
b01001010 +
#89
0#
#90
1#
b01010101 +
#91
0#
#92
1#
b01010111 +
#93
0#
#94
1#
#95
0#
#96
1#
b01010001 +
#97
0#
#98
1#
b01100010 +
#99
0#
#100
1#
b01010001 +
#101
0#
#102
1#
b01011111 +
#103
0#
#104
1#
b01100101 +
#105
0#
#106
1#
b01101000 +
#107
0#
#108
1#
b01101011 +
#109
0#
#110
1#
b01100011 +
#111
0#
#112
1#
b01100100 +
#113
0#
#114
1#
b01011111 +
#115
0#
#116
1#
b01000101 +
#117
0#
#118
1#
b01100000 +
#119
0#
#120
1#
b01011011 +
#121
0#
#122
1#
b01011111 +
#123
0#
#124
1#
b01100110 +
#125
0#
#126
1#
b01110111 +
#127
0#
#128
1#
b01100011 +
#129
0#
#130
1#
b01100110 +
#131
0#
#132
1#
b01101110 +
#133
0#
#134
1#
b01100001 +
#135
0#
#136
1#
b01011110 +
#137
0#
#138
1#
b01110100 +
#139
0#
#140
1#
b01101110 +
#141
0#
#142
1#
b01101001 +
#143
0#
#144
1#
b10000001 +
#145
0#
#146
1#
b10000011 +
#147
0#
#148
1#
b01110101 +
#149
0#
#150
1#
b01110000 +
#151
0#
#152
1#
b01111011 +
#153
0#
#154
1#
b10000010 +
#155
0#
#156
1#
b10000110 +
#157
0#
#158
1#
b01110011 +
#159
0#
#160
1#
b01110001 +
#161
0#
#162
1#
b01110011 +
#163
0#
#164
1#
b01110100 +
#165
0#
#166
1#
b01101101 +
#167
0#
#168
1#
b01101110 +
#169
0#
#170
1#
b01111100 +
#171
0#
#172
1#
b01111011 +
#173
0#
#174
1#
b01111111 +
#175
0#
#176
1#
b01101111 +
#177
0#
#178
1#
b01111110 +
#179
0#
#180
1#
b01110010 +
#181
0#
#182
1#
b01111010 +
#183
0#
#184
1#
#185
0#
#186
1#
#187
0#
#188
1#
b01100101 +
#189
0#
#190
1#
b01110000 +
#191
0#
#192
1#
b01100001 +
#193
0#
#194
1#
b01100010 +
#195
0#
#196
1#
b01101000 +
#197
0#
#198
1#
b01101100 +
#199
0#
#200
1#
b01100111 +
#201
0#
#202
1#
b01101010 +
#203
0#
#204
1#
b01100101 +
#205
0#
#206
1#
b01110100 +
#207
0#
#208
1#
b01100111 +
#209
0#
#210
1#
b01111011 +
#211
0#
#212
1#
b01101100 +
#213
0#
#214
1#
b01110010 +
#215
0#
#216
1#
b01100000 +
#217
0#
#218
1#
b01110101 +
#219
0#
#220
1#
b01101110 +
#221
0#
#222
1#
b01100100 +
#223
0#
#224
1#
b01100011 +
#225
0#
#226
1#
#227
0#
#228
1#
b01101000 +
#229
0#
#230
1#
b01011100 +
#231
0#
#232
1#
b01100011 +
#233
0#
#234
1#
b01011101 +
#235
0#
#236
1#
b01101010 +
#237
0#
#238
1#
b01101011 +
#239
0#
#240
1#
b01101001 +
#241
0#
#242
1#
b01101011 +
#243
0#
#244
1#
b01011101 +
#245
0#
#246
1#
b01110000 +
#247
0#
#248
1#
b01011101 +
#249
0#
#250
1#
#251
0#
#252
1#
b01001000 +
#253
0#
#254
1#
b01010100 +
#255
0#
#256
1#
b01001110 +
#257
0#
#258
1#
b01001111 +
#259
0#
#260
1#
b01010001 +
#261
0#
#262
1#
b01000101 +
#263
0#
#264
1#
b01001101 +
#265
0#
#266
1#
b01011001 +
#267
0#
#268
1#
b01011011 +
#269
0#
#270
1#
b01101010 +
#271
0#
#272
1#
b01101111 +
#273
0#
#274
1#
b01100100 +
#275
0#
#276
1#
b01101010 +
#277
0#
#278
1#
b01101000 +
#279
0#
#280
1#
b01011010 +
#281
0#
#282
1#
b01100111 +
#283
0#
#284
1#
b01011010 +
#285
0#
#286
1#
b01011001 +
#287
0#
#288
1#
b01011110 +
#289
0#
#290
1#
b01010000 +
#291
0#
#292
1#
b01000110 +
#293
0#
#294
1#
b01001110 +
#295
0#
#296
1#
b01010111 +
#297
0#
#298
1#
b01100100 +
#299
0#
#300
1#
b01101010 +
#301
0#
#302
1#
b01111100 +
#303
0#
#304
1#
b01101011 +
#305
0#
#306
1#
b01101101 +
#307
0#
#308
1#
b01110010 +
#309
0#
#310
1#
b01111001 +
#311
0#
#312
1#
b01111101 +
#313
0#
#314
1#
b01110001 +
#315
0#
#316
1#
b01111000 +
#317
0#
#318
1#
b01111100 +
#319
0#
#320
1#
b01111010 +
#321
0#
#322
1#
b01101000 +
#323
0#
#324
1#
b01110101 +
#325
0#
#326
1#
b01110110 +
#327
0#
#328
1#
b01011011 +
#329
0#
#330
1#
b01100111 +
#331
0#
#332
1#
b01100000 +
#333
0#
#334
1#
b01101101 +
#335
0#
#336
1#
b01101110 +
#337
0#
#338
1#
b01101101 +
#339
0#
#340
1#
b01111101 +
#341
0#
#342
1#
b01110010 +
#343
0#
#344
1#
b01110101 +
#345
0#
#346
1#
b10000011 +
#347
0#
#348
1#
b10010100 +
#349
0#
#350
1#
b10010101 +
#351
0#
#352
1#
b10001000 +
#353
0#
#354
1#
b10001001 +
#355
0#
#356
1#
#357
0#
#358
1#
b01111100 +
#359
0#
#360
1#
b10000111 +
#361
0#
#362
1#
b01111110 +
#363
0#
#364
1#
b01100101 +
#365
0#
#366
1#
b01100110 +
#367
0#
#368
1#
b01010111 +
#369
0#
#370
1#
b01011101 +
#371
0#
#372
1#
b01011110 +
#373
0#
#374
1#
b01001111 +
#375
0#
#376
1#
b01010111 +
#377
0#
#378
1#
b01010101 +
#379
0#
#380
1#
b01010110 +
#381
0#
#382
1#
b01001011 +
#383
0#
#384
1#
b01010100 +
#385
0#
#386
1#
b01101010 +
#387
0#
#388
1#
b01101011 +
#389
0#
#390
1#
b01100011 +
#391
0#
#392
1#
b01101011 +
#393
0#
#394
1#
b01110000 +
#395
0#
#396
1#
b01111000 +
#397
0#
#398
1#
b01110001 +
#399
0#
#400
1#
b01101101 +
#401
0#
#402
1#
b01101111 +
#403
0#
#404
1#
b01110010 +
#405
0#
#406
1#
b01111101 +
#407
0#
#408
1#
b10000100 +
#409
0#
#410
1#
b01101011 +
#411
0#
#412
1#
b01110100 +
#413
0#
#414
1#
b01110000 +
#415
0#
#416
1#
b01011100 +
#417
0#
#418
1#
b01101010 +
#419
0#
#420
1#
b01011110 +
#421
0#
#422
1#
b01010011 +
#423
0#
#424
1#
b01011100 +
#425
0#
#426
1#
b01011101 +
#427
0#
#428
1#
b01010111 +
#429
0#
#430
1#
b01011101 +
#431
0#
#432
1#
#433
0#
#434
1#
b01010111 +
#435
0#
#436
1#
b01100001 +
#437
0#
#438
1#
b01101100 +
#439
0#
#440
1#
b01101001 +
#441
0#
#442
1#
b01100111 +
#443
0#
#444
1#
b01101110 +
#445
0#
#446
1#
b01100101 +
#447
0#
#448
1#
b01110011 +
#449
0#
#450
1#
b01110111 +
#451
0#
#452
1#
b01011110 +
#453
0#
#454
1#
b01110000 +
#455
0#
#456
1#
b01110101 +
#457
0#
#458
1#
b01010101 +
#459
0#
#460
1#
b01011010 +
#461
0#
#462
1#
b01100101 +
#463
0#
#464
1#
b01101010 +
#465
0#
#466
1#
b01111001 +
#467
0#
#468
1#
b01100100 +
#469
0#
#470
1#
b01010111 +
#471
0#
#472
1#
#473
0#
#474
1#
b01010110 +
#475
0#
#476
1#
b01011001 +
#477
0#
#478
1#
b01100101 +
#479
0#
#480
1#
#481
0#
#482
1#
b01101000 +
#483
0#
#484
1#
b01011101 +
#485
0#
#486
1#
b01010001 +
#487
0#
#488
1#
b01101011 +
#489
0#
#490
1#
b01100101 +
#491
0#
#492
1#
b01110011 +
#493
0#
#494
1#
b01011110 +
#495
0#
#496
1#
b01011100 +
#497
0#
#498
1#
b01101010 +
#499
0#
#500
1#
b01110011 +
#501
0#
#502
1#
b01100100 +
#503
0#
#504
1#
b01100110 +
#505
0#
#506
1#
b01101100 +
#507
0#
#508
1#
b01110000 +
#509
0#
#510
1#
b01100011 +
#511
0#
#512
1#
b01101111 +
#513
0#
#514
1#
b01110010 +
#515
0#
#516
1#
b01101001 +
#517
0#
#518
1#
b01101111 +
#519
0#
#520
1#
b01110100 +
#521
0#
#522
1#
b01011111 +
#523
0#
#524
1#
b01101010 +
#525
0#
#526
1#
b01011101 +
#527
0#
#528
1#
b01101010 +
#529
0#
#530
1#
b01100100 +
#531
0#
#532
1#
b01010101 +
#533
0#
#534
1#
b01010001 +
#535
0#
#536
1#
b01011101 +
#537
0#
#538
1#
b01101111 +
#539
0#
#540
1#
b01010111 +
#541
0#
#542
1#
b01010110 +
#543
0#
#544
1#
b01011011 +
#545
0#
#546
1#
#547
0#
#548
1#
b01100010 +
#549
0#
#550
1#
b01100111 +
#551
0#
#552
1#
b01101000 +
#553
0#
#554
1#
b01101001 +
#555
0#
#556
1#
b01101011 +
#557
0#
#558
1#
b01101001 +
#559
0#
#560
1#
b01101100 +
#561
0#
#562
1#
b01110110 +
#563
0#
#564
1#
b01111010 +
#565
0#
#566
1#
b10001001 +
#567
0#
#568
1#
b10001010 +
#569
0#
#570
1#
b10011001 +
#571
0#
#572
1#
b10001111 +
#573
0#
#574
1#
b10001011 +
#575
0#
#576
1#
b10001010 +
#577
0#
#578
1#
b10001001 +
#579
0#
#580
1#
b10000001 +
#581
0#
#582
1#
b10000111 +
#583
0#
#584
1#
b10000110 +
#585
0#
#586
1#
b10000100 +
#587
0#
#588
1#
b10010100 +
#589
0#
#590
1#
b10000010 +
#591
0#
#592
1#
b01111101 +
#593
0#
#594
1#
b10001000 +
#595
0#
#596
1#
b01110100 +
#597
0#
#598
1#
b01111010 +
#599
0#
#600
1#
#601
0#
#602
1#
b01011111 +
#603
0#
#604
1#
b01101001 +
#605
0#
#606
1#
b01100011 +
#607
0#
#608
1#
b01010110 +
#609
0#
#610
1#
b01011010 +
#611
0#
#612
1#
b00111110 +
#613
0#
#614
1#
b01001101 +
#615
0#
#616
1#
b01011101 +
#617
0#
#618
1#
b01011010 +
#619
0#
#620
1#
b01100110 +
#621
0#
#622
1#
b01100001 +
#623
0#
#624
1#
b01011000 +
#625
0#
#626
1#
b01011001 +
#627
0#
#628
1#
b01011111 +
#629
0#
#630
1#
b01011100 +
#631
0#
#632
1#
b01011011 +
#633
0#
#634
1#
b01011100 +
#635
0#
#636
1#
b01100111 +
#637
0#
#638
1#
b01101001 +
#639
0#
#640
1#
b01110101 +
#641
0#
#642
1#
b01100001 +
#643
0#
#644
1#
b01011111 +
#645
0#
#646
1#
#647
0#
#648
1#
b01001110 +
#649
0#
#650
1#
b01011011 +
#651
0#
#652
1#
b01011101 +
#653
0#
#654
1#
b01011111 +
#655
0#
#656
1#
b01100110 +
#657
0#
#658
1#
b01110011 +
#659
0#
#660
1#
b01101110 +
#661
0#
#662
1#
b01110011 +
#663
0#
#664
1#
b01011110 +
#665
0#
#666
1#
b01010001 +
#667
0#
#668
1#
b01100001 +
#669
0#
#670
1#
b01011101 +
#671
0#
#672
1#
b01100111 +
#673
0#
#674
1#
b01100100 +
#675
0#
#676
1#
b01101000 +
#677
0#
#678
1#
b01011100 +
#679
0#
#680
1#
b01001010 +
#681
0#
#682
1#
b01100000 +
#683
0#
#684
1#
b01010110 +
#685
0#
#686
1#
b01011110 +
#687
0#
#688
1#
b01010111 +
#689
0#
#690
1#
b01011011 +
#691
0#
#692
1#
b01011111 +
#693
0#
#694
1#
b01011001 +
#695
0#
#696
1#
b01100010 +
#697
0#
#698
1#
b01010011 +
#699
0#
#700
1#
b01010100 +
#701
0#
#702
1#
b01011111 +
#703
0#
#704
1#
b01011011 +
#705
0#
#706
1#
b01101110 +
#707
0#
#708
1#
b01011101 +
#709
0#
#710
1#
b01011110 +
#711
0#
#712
1#
b01010010 +
#713
0#
#714
1#
b01011111 +
#715
0#
#716
1#
b01011110 +
#717
0#
#718
1#
b01100100 +
#719
0#
#720
1#
b01100011 +
#721
0#
#722
1#
b01011010 +
#723
0#
#724
1#
b01101111 +
#725
0#
#726
1#
b01110110 +
#727
0#
#728
1#
b01111000 +
#729
0#
#730
1#
b01111110 +
#731
0#
#732
1#
b10000010 +
#733
0#
#734
1#
b10000110 +
#735
0#
#736
1#
b10001010 +
#737
0#
#738
1#
b10001001 +
#739
0#
#740
1#
b10010000 +
#741
0#
#742
1#
b10001100 +
#743
0#
#744
1#
b01111011 +
#745
0#
#746
1#
b01111101 +
#747
0#
#748
1#
b01111000 +
#749
0#
#750
1#
b01110110 +
#751
0#
#752
1#
b01100111 +
#753
0#
#754
1#
#755
0#
#756
1#
b01011111 +
#757
0#
#758
1#
b01010100 +
#759
0#
#760
1#
b01010011 +
#761
0#
#762
1#
b01000101 +
#763
0#
#764
1#
b01001111 +
#765
0#
#766
1#
#767
0#
#768
1#
b01001110 +
#769
0#
#770
1#
b01011100 +
#771
0#
#772
1#
b01101100 +
#773
0#
#774
1#
b01110110 +
#775
0#
#776
1#
#777
0#
#778
1#
b01110010 +
#779
0#
#780
1#
b01100010 +
#781
0#
#782
1#
b01110010 +
#783
0#
#784
1#
b01110001 +
#785
0#
#786
1#
b01100111 +
#787
0#
#788
1#
b01100011 +
#789
0#
#790
1#
b01011000 +
#791
0#
#792
1#
b01011010 +
#793
0#
#794
1#
b01010011 +
#795
0#
#796
1#
b01011001 +
#797
0#
#798
1#
b01010101 +
#799
0#
#800
1#
b01011110 +
#801
0#
#802
1#
b01010110 +
#803
0#
#804
1#
b01010101 +
#805
0#
#806
1#
b01011000 +
#807
0#
#808
1#
b01001101 +
#809
0#
#810
1#
b01010000 +
#811
0#
#812
1#
b01010011 +
#813
0#
#814
1#
b01010001 +
#815
0#
#816
1#
b01101011 +
#817
0#
#818
1#
b01110011 +
#819
0#
#820
1#
b01110110 +
#821
0#
#822
1#
b01111100 +
#823
0#
#824
1#
b01101010 +
#825
0#
#826
1#
b01100011 +
#827
0#
#828
1#
b01011001 +
#829
0#
#830
1#
b01100000 +
#831
0#
#832
1#
b01100001 +
#833
0#
#834
1#
b01100010 +
#835
0#
#836
1#
b01011111 +
#837
0#
#838
1#
b01011011 +
#839
0#
#840
1#
b01110000 +
#841
0#
#842
1#
b01100110 +
#843
0#
#844
1#
b01101011 +
#845
0#
#846
1#
b01100000 +
#847
0#
#848
1#
b01111110 +
#849
0#
#850
1#
b01111010 +
#851
0#
#852
1#
#853
0#
#854
1#
b10000000 +
#855
0#
#856
1#
b01110110 +
#857
0#
#858
1#
b01110100 +
#859
0#
#860
1#
b01101110 +
#861
0#
#862
1#
b01110001 +
#863
0#
#864
1#
b01101000 +
#865
0#
#866
1#
#867
0#
#868
1#
b01110000 +
#869
0#
#870
1#
b01100110 +
#871
0#
#872
1#
b01101010 +
#873
0#
#874
1#
b01101001 +
#875
0#
#876
1#
b01100110 +
#877
0#
#878
1#
b01110001 +
#879
0#
#880
1#
b01101111 +
#881
0#
#882
1#
b01100010 +
#883
0#
#884
1#
b01101110 +
#885
0#
#886
1#
b01011011 +
#887
0#
#888
1#
b01101010 +
#889
0#
#890
1#
b01100111 +
#891
0#
#892
1#
b01111101 +
#893
0#
#894
1#
b01101101 +
#895
0#
#896
1#
b01110100 +
#897
0#
#898
1#
b01100001 +
#899
0#
#900
1#
b01101001 +
#901
0#
#902
1#
b01011101 +
#903
0#
#904
1#
b01101011 +
#905
0#
#906
1#
b01110000 +
#907
0#
#908
1#
b01111100 +
#909
0#
#910
1#
b01110101 +
#911
0#
#912
1#
b01110010 +
#913
0#
#914
1#
b01101110 +
#915
0#
#916
1#
b01100011 +
#917
0#
#918
1#
b01110101 +
#919
0#
#920
1#
b01101101 +
#921
0#
#922
1#
b01101000 +
#923
0#
#924
1#
b01100011 +
#925
0#
#926
1#
b01110000 +
#927
0#
#928
1#
b01101001 +
#929
0#
#930
1#
b01100011 +
#931
0#
#932
1#
b01011100 +
#933
0#
#934
1#
b01001111 +
#935
0#
#936
1#
b01100000 +
#937
0#
#938
1#
b01011010 +
#939
0#
#940
1#
b01101011 +
#941
0#
#942
1#
b01101010 +
#943
0#
#944
1#
b01011000 +
#945
0#
#946
1#
b01011010 +
#947
0#
#948
1#
#949
0#
#950
1#
b01011110 +
#951
0#
#952
1#
b01100010 +
#953
0#
#954
1#
b01101101 +
#955
0#
#956
1#
b01111011 +
#957
0#
#958
1#
b01110101 +
#959
0#
#960
1#
b01111011 +
#961
0#
#962
1#
#963
0#
#964
1#
b10000101 +
#965
0#
#966
1#
b01111100 +
#967
0#
#968
1#
#969
0#
#970
1#
b01110101 +
#971
0#
#972
1#
b01111110 +
#973
0#
#974
1#
b01110110 +
#975
0#
#976
1#
b01111001 +
#977
0#
#978
1#
#979
0#
#980
1#
b01110111 +
#981
0#
#982
1#
b01101101 +
#983
0#
#984
1#
b01110001 +
#985
0#
#986
1#
b01110000 +
#987
0#
#988
1#
b01100000 +
#989
0#
#990
1#
b01101111 +
#991
0#
#992
1#
b01101010 +
#993
0#
#994
1#
b01110010 +
#995
0#
#996
1#
b01101101 +
#997
0#
#998
1#
b01100110 +
#999
0#
#1000
1#
b01110111 +
#1001
0#
#1002
1#
b01110011 +
#1003
0#
#1004
1#
b01101011 +
#1005
0#
#1006
1#
b01100101 +
#1007
0#
#1008
1#
b01101111 +
#1009
0#
#1010
1#
b01110110 +
#1011
0#
#1012
1#
b01110000 +
#1013
0#
#1014
1#
b01100100 +
#1015
0#
#1016
1#
b01011000 +
#1017
0#
#1018
1#
b01011001 +
#1019
0#
#1020
1#
b01011010 +
#1021
0#
#1022
1#
b01011000 +
#1023
0#
#1024
1#
b01011001 +
#1025
0#
#1026
1#
b01111001 +
#1027
0#
#1028
1#
b01110010 +
#1029
0#
#1030
1#
b01111001 +
#1031
0#
#1032
1#
b01110111 +
#1033
0#
#1034
1#
b01111000 +
#1035
0#
#1036
1#
b01111001 +
#1037
0#
#1038
1#
b10000001 +
#1039
0#
#1040
1#
b10000000 +
#1041
0#
#1042
1#
b01111111 +
#1043
0#
#1044
1#
b10000001 +
#1045
0#
#1046
1#
b01110111 +
#1047
0#
#1048
1#
b01111110 +
#1049
0#
#1050
1#
b01110001 +
#1051
0#
#1052
1#
b01011100 +
#1053
0#
#1054
1#
#1055
0#
#1056
1#
b01011000 +
#1057
0#
#1058
1#
b01011110 +
#1059
0#
#1060
1#
b01011010 +
#1061
0#
#1062
1#
b01011011 +
#1063
0#
#1064
1#
b01011010 +
#1065
0#
#1066
1#
b01001101 +
#1067
0#
#1068
1#
b01001010 +
#1069
0#
#1070
1#
b01000110 +
#1071
0#
#1072
1#
b01010001 +
#1073
0#
#1074
1#
b01011010 +
#1075
0#
#1076
1#
b01101000 +
#1077
0#
#1078
1#
b01101110 +
#1079
0#
#1080
1#
b01101011 +
#1081
0#
#1082
1#
b01110000 +
#1083
0#
#1084
1#
b01110101 +
#1085
0#
#1086
1#
b01111010 +
#1087
0#
#1088
1#
b01111100 +
#1089
0#
#1090
1#
b01101110 +
#1091
0#
#1092
1#
b01110101 +
#1093
0#
#1094
1#
b10000000 +
#1095
0#
#1096
1#
b10001110 +
#1097
0#
#1098
1#
b10001101 +
#1099
0#
#1100
1#
b01111001 +
#1101
0#
#1102
1#
b01101000 +
#1103
0#
#1104
1#
b01010000 +
#1105
0#
#1106
1#
b01000110 +
#1107
0#
#1108
1#
b01000100 +
#1109
0#
#1110
1#
b01000000 +
#1111
0#
#1112
1#
b01000011 +
#1113
0#
#1114
1#
b01000100 +
#1115
0#
#1116
1#
b01010010 +
#1117
0#
#1118
1#
b01010011 +
#1119
0#
#1120
1#
b01010000 +
#1121
0#
#1122
1#
b01010011 +
#1123
0#
#1124
1#
b01011110 +
#1125
0#
#1126
1#
b01010011 +
#1127
0#
#1128
1#
b01011100 +
#1129
0#
#1130
1#
#1131
0#
#1132
1#
b01100010 +
#1133
0#
#1134
1#
b01101001 +
#1135
0#
#1136
1#
b01100101 +
#1137
0#
#1138
1#
b01101011 +
#1139
0#
#1140
1#
b01101001 +
#1141
0#
#1142
1#
b01011011 +
#1143
0#
#1144
1#
b01100010 +
#1145
0#
#1146
1#
b01100110 +
#1147
0#
#1148
1#
b01011110 +
#1149
0#
#1150
1#
b01100100 +
#1151
0#
#1152
1#
#1153
0#
#1154
1#
b01101100 +
#1155
0#
#1156
1#
b01110101 +
#1157
0#
#1158
1#
b01110001 +
#1159
0#
#1160
1#
b01110110 +
#1161
0#
#1162
1#
b01101100 +
#1163
0#
#1164
1#
b01110010 +
#1165
0#
#1166
1#
b01101101 +
#1167
0#
#1168
1#
#1169
0#
#1170
1#
b01101100 +
#1171
0#
#1172
1#
b01101011 +
#1173
0#
#1174
1#
b01101001 +
#1175
0#
#1176
1#
b01110001 +
#1177
0#
#1178
1#
b01101110 +
#1179
0#
#1180
1#
b01101111 +
#1181
0#
#1182
1#
#1183
0#
#1184
1#
b01110100 +
#1185
0#
#1186
1#
b01110101 +
#1187
0#
#1188
1#
b01110010 +
#1189
0#
#1190
1#
b01111001 +
#1191
0#
#1192
1#
b01110000 +
#1193
0#
#1194
1#
b01111011 +
#1195
0#
#1196
1#
b01111010 +
#1197
0#
#1198
1#
b10000101 +
#1199
0#
#1200
1#
b10001001 +
#1201
0#
#1202
1#
b10001111 +
#1203
0#
#1204
1#
b01111110 +
#1205
0#
#1206
1#
b01110111 +
#1207
0#
#1208
1#
#1209
0#
#1210
1#
b01110011 +
#1211
0#
#1212
1#
b01101001 +
#1213
0#
#1214
1#
b01100010 +
#1215
0#
#1216
1#
b01011110 +
#1217
0#
#1218
1#
#1219
0#
#1220
1#
b01001101 +
#1221
0#
#1222
1#
b01010111 +
#1223
0#
#1224
1#
b01010011 +
#1225
0#
#1226
1#
b01010001 +
#1227
0#
#1228
1#
b01010100 +
#1229
0#
#1230
1#
b01101001 +
#1231
0#
#1232
1#
#1233
0#
#1234
1#
b01111100 +
#1235
0#
#1236
1#
b01110001 +
#1237
0#
#1238
1#
b01101110 +
#1239
0#
#1240
1#
b01101011 +
#1241
0#
#1242
1#
b01100010 +
#1243
0#
#1244
1#
b01100111 +
#1245
0#
#1246
1#
b01011000 +
#1247
0#
#1248
1#
b01100011 +
#1249
0#
#1250
1#
b01011101 +
#1251
0#
#1252
1#
b01100110 +
#1253
0#
#1254
1#
b01101000 +
#1255
0#
#1256
1#
b01101001 +
#1257
0#
#1258
1#
b01100101 +
#1259
0#
#1260
1#
b01011110 +
#1261
0#
#1262
1#
b01101100 +
#1263
0#
#1264
1#
b01101110 +
#1265
0#
#1266
1#
b01100100 +
#1267
0#
#1268
1#
b01100001 +
#1269
0#
#1270
1#
b01110000 +
#1271
0#
#1272
1#
b01110010 +
#1273
0#
#1274
1#
b01110100 +
#1275
0#
#1276
1#
b01100110 +
#1277
0#
#1278
1#
b01011000 +
#1279
0#
#1280
1#
b01101001 +
#1281
0#
#1282
1#
b01011011 +
#1283
0#
#1284
1#
b01010111 +
#1285
0#
#1286
1#
b01100001 +
#1287
0#
#1288
1#
b01011001 +
#1289
0#
#1290
1#
b01011010 +
#1291
0#
#1292
1#
#1293
0#
#1294
1#
b01100101 +
#1295
0#
#1296
1#
b01110010 +
#1297
0#
#1298
1#
b01100110 +
#1299
0#
#1300
1#
b01110110 +
#1301
0#
#1302
1#
b01110010 +
#1303
0#
#1304
1#
b01110011 +
#1305
0#
#1306
1#
b01101100 +
#1307
0#
#1308
1#
b01101101 +
#1309
0#
#1310
1#
b01110011 +
#1311
0#
#1312
1#
b01101110 +
#1313
0#
#1314
1#
b01101001 +
#1315
0#
#1316
1#
b01011110 +
#1317
0#
#1318
1#
b01010011 +
#1319
0#
#1320
1#
b01010000 +
#1321
0#
#1322
1#
b01010011 +
#1323
0#
#1324
1#
b01010111 +
#1325
0#
#1326
1#
b01010101 +
#1327
0#
#1328
1#
b01100000 +
#1329
0#
#1330
1#
b01011111 +
#1331
0#
#1332
1#
b01101001 +
#1333
0#
#1334
1#
b01100101 +
#1335
0#
#1336
1#
b01100110 +
#1337
0#
#1338
1#
b01100001 +
#1339
0#
#1340
1#
b01011000 +
#1341
0#
#1342
1#
b01100010 +
#1343
0#
#1344
1#
b01011111 +
#1345
0#
#1346
1#
b01011110 +
#1347
0#
